<mpxconfig node_version='1.4'>
  <node name='/' node_id='120001' module=''  config_builder=''  inherant='false' description='Mediator 2500'>
    <node name='aliases' node_id='480' module='mpx.service.aliases.factory'  config_builder=''  inherant='true' description='aka shortcuts, nicknames and links'>
      <config>
        <property name='__type__' value='point'/>
        <property name='priority' value='2'/>
      </config>
    </node>
    <node name='interfaces' node_id='120004' module='mpx.ion.host.mediator_2500'  config_builder=''  inherant='true' description='Physical interfaces to devices'>
      <config>
        <property name='__type__' value='point'/>
        <property name='priority' value='1'/>
      </config>
      <node name='DI1' node_id='171' module=''  config_builder=''  inherant='true' description='Digital input on counter1'>
      </node>
      <node name='DI2' node_id='172' module=''  config_builder=''  inherant='true' description='Digital input on counter2'>
      </node>
      <node name='DI3' node_id='173' module=''  config_builder=''  inherant='true' description='Digital input on counter3'>
      </node>
      <node name='DI4' node_id='174' module=''  config_builder=''  inherant='true' description='Digital input on counter4'>
      </node>
      <node name='com1' node_id='120010' module=''  config_builder=''  inherant='true' description='RS232 port, DB9 connector'>
        <config>
          <property name='__type__' value='port'/>
          <property name='debug' value='0'/>
          <property name='baud' value='9600'/>
          <property name='VTIME' value='10'/>
          <property name='stop_bits' value='1'/>
          <property name='parity' value='none'/>
          <property name='bits' value='8'/>
          <property name='flow_control' value='none'/>
          <property name='VMIN' value='0'/>
        </config>
      </node>
      <node name='com2' node_id='3' module=''  config_builder=''  inherant='true' description='RS232 port, DB9 connector'>
        <config>
          <property name='__type__' value='port'/>
          <property name='baud' value='9600'/>
          <property name='VTIME' value='10'/>
          <property name='stop_bits' value='1'/>
          <property name='parity' value='none'/>
          <property name='bits' value='8'/>
          <property name='flow_control' value='none'/>
          <property name='VMIN' value='0'/>
        </config>
      </node>
      <node name='com3' node_id='167' module=''  config_builder=''  inherant='true' description='RS485 port, Phoenix connector'>
        <config>
          <property name='__type__' value='port'/>
          <property name='debug' value='0'/>
          <property name='baud' value='9600'/>
          <property name='VTIME' value='10'/>
          <property name='stop_bits' value='1'/>
          <property name='parity' value='none'/>
          <property name='bits' value='8'/>
          <property name='flow_control' value='none'/>
          <property name='custom_baud' value='76800'/>
          <property name='VMIN' value='0'/>
        </config>
      </node>
      <node name='com4' node_id='168' module=''  config_builder=''  inherant='true' description='RS485 port, Phoenix connector'>
        <config>
          <property name='__type__' value='port'/>
          <property name='debug' value='0'/>
          <property name='baud' value='9600'/>
          <property name='VTIME' value='10'/>
          <property name='stop_bits' value='1'/>
          <property name='parity' value='none'/>
          <property name='bits' value='8'/>
          <property name='flow_control' value='none'/>
          <property name='custom_baud' value='76800'/>
          <property name='VMIN' value='0'/>
        </config>
      </node>
      <node name='com5' node_id='120039' module=''  config_builder=''  inherant='true' description='RS485 port, Phoenix connector'>
        <config>
          <property name='__type__' value='port'/>
          <property name='debug' value='0'/>
          <property name='baud' value='9600'/>
          <property name='VTIME' value='10'/>
          <property name='stop_bits' value='1'/>
          <property name='parity' value='none'/>
          <property name='bits' value='8'/>
          <property name='flow_control' value='none'/>
          <property name='custom_baud' value='76800'/>
          <property name='VMIN' value='0'/>
        </config>
      </node>
      <node name='com6' node_id='120040' module=''  config_builder=''  inherant='true' description='RS485 port, Phoenix connector'>
        <config>
          <property name='__type__' value='port'/>
          <property name='debug' value='0'/>
          <property name='baud' value='9600'/>
          <property name='VTIME' value='10'/>
          <property name='stop_bits' value='1'/>
          <property name='parity' value='none'/>
          <property name='bits' value='8'/>
          <property name='flow_control' value='none'/>
          <property name='custom_baud' value='76800'/>
          <property name='VMIN' value='0'/>
        </config>
      </node>
      <node name='console' node_id='163' module=''  config_builder=''  inherant='true' description='RS232 console port, DB9 connector'>
        <config>
          <property name='__type__' value='port'/>
          <property name='debug' value='0'/>
          <property name='baud' value='9600'/>
          <property name='stop_bits' value='1'/>
          <property name='parity' value='none'/>
          <property name='bits' value='8'/>
          <property name='flow_control' value='none'/>
        </config>
      </node>
      <node name='counter1' node_id='162' module=''  config_builder=''  inherant='true' description='Counter input'>
        <config>
          <property name='__type__' value='point'/>
        </config>
      </node>
      <node name='counter2' node_id='161' module=''  config_builder=''  inherant='true' description='Counter input'>
        <config>
          <property name='__type__' value='point'/>
        </config>
      </node>
      <node name='counter3' node_id='169' module=''  config_builder=''  inherant='true' description='Counter input'>
        <config>
          <property name='__type__' value='point'/>
        </config>
      </node>
      <node name='counter4' node_id='170' module=''  config_builder=''  inherant='true' description='Counter input'>
        <config>
          <property name='__type__' value='point'/>
        </config>
      </node>
      <node name='dallas1' node_id='159' module=''  config_builder=''  inherant='true' description='Dallas bus'>
      </node>
      <node name='dallas2' node_id='160' module=''  config_builder=''  inherant='true' description='Dallas bus'>
      </node>
      <node name='dallas3' node_id='175' module=''  config_builder=''  inherant='true' description='Dallas bus'>
      </node>
      <node name='dallas4' node_id='176' module=''  config_builder=''  inherant='true' description='Dallas bus'>
      </node>
      <node name='eth0' node_id='a7cfc6e5-09ea-4680-a346-b7f3cf2c3ceb' module='mpx.ion.host.eth.factory'  config_builder=''  inherant='true' description='Ethernet Port, 10/100BaseT'>
      </node>
      <node name='eth1' node_id='9a960435-27de-4a3d-9ce6-e0115012cd92' module='mpx.ion.host.eth.factory'  config_builder=''  inherant='true' description='Ethernet Port, 10/100BaseT'>
      </node>
      <node name='modem' node_id='509' module='mpx.ion.host.modem.InternalModem'  config_builder=''  inherant='true' description='Optional Internal Modem'>
        <config>
          <property name='__type__' value='port'/>
          <property name='debug' value='0'/>
          <property name='baud' value='57600'/>
          <property name='stop_bits' value='1'/>
          <property name='parity' value='none'/>
          <property name='bits' value='8'/>
          <property name='flow_control' value='Xon/Xoff'/>
          <property name='init_string' value='AT&amp;s0&amp;d2&amp;k3Q0V1H0'/>
          <property name='enable' value='1'/>
        </config>
        <node name='ppp0' node_id='518' module='mpx.ion.host.modem.ppp.factory'  config_builder=''  inherant='true' description='PPP over a comm port or modem'>
          <config>
            <property name='__type__' value='service'/>
            <property name='debug' value='0'/>
            <property name='advanced_options'>
              <list>
              </list>
            </property>
            <property name='override_defaultroute' value='1'/>
            <property name='noipdefault' value='1'/>
            <property name='mru' value='876'/>
            <property name='mtu' value='876'/>
            <property name='enable' value='1'/>
          </config>
          <node name='incoming' node_id='783' module='mpx.ion.host.modem.ppp.Incoming'  config_builder=''  inherant='true' description='PPP0 incoming connection'>
            <config>
              <property name='__type__' value='service'/>
              <property name='debug' value='0'/>
              <property name='user_id' value='pppuser'/>
              <property name='enable_autoppp' value='0'/>
              <property name='enable' value='0'/>
            </config>
          </node>
          <node name='outgoing' node_id='782' module='mpx.ion.host.modem.ppp.Outgoing'  config_builder=''  inherant='true' description='PPP0 outgoing connection'>
            <config>
              <property name='__type__' value='service'/>
              <property name='debug' value='0'/>
              <property name='on_demand' value='1'/>
              <property name='routes'>
                <list>
                </list>
              </property>
              <property name='enable' value='0'/>
            </config>
          </node>
        </node>
      </node>
      <node name='relay1' node_id='177' module=''  config_builder=''  inherant='true' description='dry contact closure'>
      </node>
      <node name='relay2' node_id='179' module=''  config_builder=''  inherant='true' description='dry contact closure'>
      </node>
      <node name='usb' node_id='89c5125e-23ce-4e5e-a4c4-8a858b67d032' module='mpx.ion.host.usb.factory'  config_builder=''  inherant='true' description='USB Port'>
        <config>
          <property name='__type__' value='port'/>
          <property name='debug' value='0'/>
        </config>
        <node name='usb_storage' node_id='fb7e9100-1d50-4aad-8f8a-50f1bed0e82a' module='mpx.ion.host.usb.storage'  config_builder=''  inherant='true' description='USB Storage'>
          <config>
            <property name='__type__' value='device'/>
            <property name='debug' value='0'/>
          </config>
        </node>
      </node>
      <node name='virtuals' node_id='1122' module='mpx.lib.node.CompositeNode'  config_builder=''  inherant='true' description='Group for organizing virtual points'>
        <node name='def_value_0' node_id='515' module='mpx.lib.node.simple_value.SimpleValue'  config_builder=''  inherant='false' description='Configurable Value'>
          <config>
            <property name='__type__' value='point'/>
            <property name='debug' value='0'/>
            <property name='value' value='0.0'/>
            <property name='conversion' value='float'/>
          </config>
        </node>
        <node name='def_value_1' node_id='515' module='mpx.lib.node.simple_value.SimpleValue'  config_builder=''  inherant='false' description='Configurable Value'>
          <config>
            <property name='__type__' value='point'/>
            <property name='debug' value='0'/>
            <property name='value' value='1.0'/>
            <property name='conversion' value='float'/>
          </config>
        </node>
      </node>
    </node>
    <node name='services' node_id='468' module='mpx.service.factory'  config_builder=''  inherant='true' description='Services'>
      <config>
        <property name='__type__' value='point'/>
        <property name='priority' value='3'/>
      </config>
      <node name='alarms' node_id='812' module='mpx.lib.node.CompositeNode'  config_builder=''  inherant='true' description='Alarm manager container'>
        <node name='manager' node_id='813' module='mpx.service.alarms.AlarmManager'  config_builder=''  inherant='false' description='Manages groups of alarms'>
          <node name='alarms' node_id='818' module='mpx.lib.node.CompositeNode'  config_builder=''  inherant='true' description='Alarm container'>
          </node>
          <node name='exporters' node_id='816' module='mpx.lib.node.factory'  config_builder=''  inherant='true' description='Exporters'>
            <node name='export_log_1' node_id='841' module='mpx.service.alarms.exporter.LogAndExport'  config_builder=''  inherant='false' description='Generate log entry and export'>
              <config>
                <property name='__type__' value='point'/>
                <property name='log' value='/services/logger/fsg_exception_log'/>
              </config>
            </node>
          </node>
        </node>
      </node>
      <node name='garbage_collector' node_id='d6da9764-7a46-4103-ae1b-9b8dbd2a86fe' module=''  config_builder=''  inherant='true' description='Garbage Collector Service'>
        <config>
          <property name='__type__' value='service'/>
          <property name='debug' value='0'/>
        </config>
      </node>
      <node name='logger' node_id='479' module='mpx.service.logger.factory'  config_builder='envenergy.wizard.log.LogWizardPlugin'  inherant='true' description='The Mediator&apos;s logging services'>
        <config>
          <property name='__type__' value='point'/>
          <property name='debug' value='0'/>
          <property name='enabled' value='1'/>
        </config>
        <node name='msglog' node_id='604' module='mpx.service.logger.log'  config_builder=''  inherant='true' description='Logs messages from the Mediator Framework'>
          <config>
            <property name='__type__' value='point'/>
            <property name='minimum_size' value='250'/>
            <property name='maximum_size' value='500'/>
          </config>
          <node name='exporters' node_id='461' module='mpx.lib.node.factory'  config_builder='envenergy.wizard.log.LogWizardPlugin_ToExporters'  inherant='true' description='Exporters'>
          </node>
        </node>
        <node name='fsg_data_log' node_id='261' module='mpx.service.logger.periodic_log.factory'  config_builder='envenergy.wizard.log.LogWizardPlugin_ToLog'  inherant='false' description='Periodic log'>
          <config>
            <property name='__type__' value='point'/>
            <property name='debug' value=' 0'/>
            <property name='period' value='15'/>
            <property name='minimum_size' value='250'/>
            <property name='maximum_size' value='500'/>
          </config>
          <node name='columns' node_id='460' module='mpx.lib.node.factory'  config_builder='envenergy.wizard.log.LogWizardPlugin_ToColumns'  inherant='true' description='Log Columns'>
            <node name='timestamp' node_id='462' module='mpx.service.logger.periodic_column.factory'  config_builder=''  inherant='false' description='Timestamp column'>
              <config>
                <property name='__type__' value='point'/>
                <property name='debug' value='0'/>
                <property name='sort_order' value='ascending'/>
                <property name='position' value='0'/>
                <property name='context' value='None'/>
                <property name='args' value='()'/>
                <property name='function' value='self.scheduled_time'/>
              </config>
            </node>
          </node>
          <node name='exporters' node_id='461' module='mpx.lib.node.factory'  config_builder='envenergy.wizard.log.LogWizardPlugin_ToExporters'  inherant='true' description='Exporters'>
            <node name='periodic_exporter_fsg' node_id='333' module='mpx.service.data.periodic_exporter.factory'  config_builder='envenergy.wizard.log.LogWizardPlugin_ToExporter'  inherant='false' description='Standard periodic data exporter'>
              <config>
                <property name='__type__' value='point'/>
                <property name='debug' value='0'/>
                <property name='days' value='0'/>
                <property name='timeout' value='60'/>
                <property name='connection_attempts' value='1'/>
                <property name='always_export' value='1'/>
                <property name='enabled' value='1'/>
                <property name='hours' value='0'/>
                <property name='connection_node' value='/services/network'/>
                <property name='gm_time' value='0'/>
                <property name='minutes' value='1'/>
              </config>
              <node name='fsg_xml_formatter' node_id='79539f75-78c4-4230-9c24-110449c75742' module='mpx.service.data.fsg.xml_formatter.XMLFormatter'  config_builder=''  inherant='false' description='XML Formatter for FSG Demo Data.'>
                <config>
                  <property name='__type__' value='point'/>
                  <property name='location_info' value='MyOffice'/>
                  <property name='timestamp_format' value='%Y-%m-%dT%H:%M:%S'/>
                  <property name='panel_info' value='MyPanel'/>
                  <property name='location_key' value='123'/>
                  <property name='panel_key' value='456'/>
                </config>
              </node>
              <node name='ftp_transporter' node_id='332' module='mpx.service.data.ftp_transporter.factory'  config_builder=''  inherant='false' description='FTP transporter'>
                <config>
                  <property name='__type__' value='service'/>
                  <property name='debug' value='0'/>
                  <property name='name_scheme' value='timestamp'/>
                  <property name='password' value='mozaic'/>
                  <property name='timeout' value='60'/>
                  <property name='passive_mode' value='on'/>
                  <property name='enabled' value='1'/>
                  <property name='host' value='mother.envenergy.com'/>
                  <property name='file_suffix' value='.log'/>
                  <property name='file_prefix' value='envenergy'/>
                  <property name='username' value='spenner'/>
                </config>
              </node>
            </node>
          </node>
        </node>
        <node name='fsg_exception_log' node_id='261' module='mpx.service.logger.periodic_log.factory'  config_builder='envenergy.wizard.log.LogWizardPlugin_ToLog'  inherant='false' description='Periodic log'>
          <config>
            <property name='__type__' value='point'/>
            <property name='debug' value=' 0'/>
            <property name='period' value='0'/>
            <property name='minimum_size' value='250'/>
            <property name='maximum_size' value='500'/>
          </config>
          <node name='columns' node_id='460' module='mpx.lib.node.factory'  config_builder='envenergy.wizard.log.LogWizardPlugin_ToColumns'  inherant='true' description='Log Columns'>
            <node name='timestamp' node_id='462' module='mpx.service.logger.periodic_column.factory'  config_builder=''  inherant='true' description='Timestamp column'>
              <config>
                <property name='__type__' value='point'/>
                <property name='debug' value='0'/>
                <property name='sort_order' value='ascending'/>
                <property name='position' value='0'/>
                <property name='context' value='None'/>
                <property name='args' value='()'/>
                <property name='function' value='self.scheduled_time'/>
              </config>
            </node>
            <node name='trigger_node_url' node_id='264' module='mpx.service.logger.periodic_column.factory'  config_builder='envenergy.wizard.log.LogWizardPlugin_ToColumn'  inherant='false' description='Periodic column'>
              <config>
                <property name='__type__' value='point'/>
                <property name='debug' value='0'/>
                <property name='sort_order' value='none'/>
                <property name='position' value='1'/>
                <property name='context' value='None'/>
                <property name='args' value='()'/>
                <property name='function' value='mpx.lib.node.as_node(&quot;/interfaces/virtuals/def_value_0&quot;).get'/>
                <property name='conversion' value='magnitude'/>
              </config>
            </node>
            <node name='trigger_node_msg' node_id='264' module='mpx.service.logger.periodic_column.factory'  config_builder='envenergy.wizard.log.LogWizardPlugin_ToColumn'  inherant='false' description='Periodic column'>
              <config>
                <property name='__type__' value='point'/>
                <property name='debug' value='0'/>
                <property name='sort_order' value='none'/>
                <property name='position' value='2'/>
                <property name='context' value='None'/>
                <property name='args' value='()'/>
                <property name='function' value='mpx.lib.node.as_node(&quot;/interfaces/virtuals/def_value_0&quot;).get'/>
                <property name='conversion' value='magnitude'/>
              </config>
            </node>
          </node>
          <node name='exporters' node_id='461' module='mpx.lib.node.factory'  config_builder='envenergy.wizard.log.LogWizardPlugin_ToExporters'  inherant='true' description='Exporters'>
          </node>
        </node>
      </node>
      <node name='network' node_id='469' module='mpx.service.network.factory'  config_builder=''  inherant='true' description='The Mediator&apos;s networking services'>
        <config>
          <property name='__type__' value='point'/>
          <property name='debug' value='0'/>
          <property name='enabled' value='1'/>
        </config>
        <node name='dynamic_dns' node_id='1250' module='mpx.ion.host.eth.dyndns.factory'  config_builder=''  inherant='true' description='Dynamic DNS for Mediators connected to a DHCP server'>
          <config>
            <property name='__type__' value='service'/>
            <property name='debug' value='0'/>
            <property name='ddns_service' value='dyndns.org'/>
            <property name='minutes' value='15'/>
            <property name='enable' value='0'/>
          </config>
        </node>
        <node name='http_server' node_id='471' module='mpx.service.network.http.factory'  config_builder=''  inherant='true' description='HTTP server'>
          <config>
            <property name='__type__' value='point'/>
            <property name='debug' value='0'/>
            <property name='enabled' value='1'/>
            <property name='thread_count' value='3'/>
            <property name='port' value='${mpx.properties.HTTP_PORT}'/>
          </config>
          <node name='XMLRPCv2' node_id='07ff4603-ca5b-44ef-827b-361f8cffbba9' module='mpx.service.network.http.handlers.xmlrpc.factory'  config_builder=''  inherant='true' description=''>
          </node>
          <node name='config_file_handler' node_id='903a9305-debe-4fce-b385-d1395fd94696' module='mpx.service.network.http.handlers.config.factory'  config_builder=''  inherant='true' description='HTTP Configuration File Handler.'>
            <config>
              <property name='__type__' value='point'/>
              <property name='debug' value='0'/>
              <property name='safe_save' value='1'/>
              <property name='enabled' value='1'/>
              <property name='keep_backup' value='0'/>
            </config>
          </node>
          <node name='http_file_handler' node_id='474' module='mpx.service.network.http.request_handler.factory'  config_builder=''  inherant='true' description='HTTP File Handler.'>
            <config>
              <property name='__type__' value='point'/>
              <property name='debug' value='0'/>
              <property name='put_enabled' value='1'/>
              <property name='delete_enabled' value='1'/>
              <property name='request_path' value='/'/>
              <property name='enabled' value='1'/>
              <property name='server_root' value='${mpx.properties.HTTP_ROOT}'/>
            </config>
          </node>
          <node name='msglog_browser' node_id='450' module='mpx.lib.msglog.browser.factory'  config_builder=''  inherant='true' description='Enables browsing of the Mediator Framework Msglog'>
            <config>
              <property name='__type__' value='point'/>
              <property name='debug' value='0'/>
              <property name='request_path' value='^/msglog/.*|^/msglog$'/>
              <property name='enabled' value='1'/>
            </config>
          </node>
          <node name='node_browser' node_id='472' module='mpx.lib.node.browser.factory'  config_builder=''  inherant='true' description='Enables html browsing of Node Tree'>
            <config>
              <property name='__type__' value='point'/>
              <property name='debug' value='0'/>
              <property name='request_path' value='/nodebrowser'/>
              <property name='enabled' value='1'/>
            </config>
          </node>
          <node name='properties_browser' node_id='1246' module='mpx.service.network.http.properties_request_handler.PropertiesRequestHandler'  config_builder=''  inherant='true' description='Displays the current Properties of the system in an HTML page'>
            <config>
              <property name='__type__' value='point'/>
              <property name='debug' value='0'/>
              <property name='request_path' value='^/properties$'/>
              <property name='enabled' value='1'/>
            </config>
          </node>
          <node name='xmlrpc_handler' node_id='473' module='mpx.service.network.http.xmlrpc_handler.factory'  config_builder=''  inherant='true' description='Enables XMLRPC'>
            <config>
              <property name='__type__' value='point'/>
              <property name='debug' value='0'/>
              <property name='request_path' value='/xmlrpc'/>
              <property name='enabled' value='1'/>
              <property name='security_handler' value='DefaultSecurityHandler'/>
              <property name='deployed_objects'>
                <list>
                </list>
              </property>
            </config>
            <node name='mediator_system' node_id='802' module='mpx.lib.xmlrpc.XMLRPC_Deploy'  config_builder=''  inherant='true' description='Mediator level methods'>
              <config>
                <property name='__type__' value='point'/>
                <property name='lifetime' value='Runtime'/>
                <property name='class_name' value='mpx.lib.xmlrpc.mediator.MediatorSystem'/>
                <property name='alias' value='mediator_system'/>
              </config>
            </node>
            <node name='rna_xmlrpc' node_id='603' module='mpx.lib.xmlrpc.XMLRPC_Deploy'  config_builder=''  inherant='true' description='RNA Over XMLRPC '>
              <config>
                <property name='__type__' value='point'/>
                <property name='lifetime' value='Runtime'/>
                <property name='class_name' value='mpx.lib.xmlrpc.rna_xmlrpc.RNA_XMLRPC_Handler'/>
                <property name='alias' value='rna_xmlrpc'/>
              </config>
            </node>
            <node name='rna_xmlrpc2' node_id='130069' module='mpx.lib.xmlrpc.XMLRPC_Deploy'  config_builder=''  inherant='true' description='RNA Over XMLRPC with  settable encodings'>
              <config>
                <property name='__type__' value='point'/>
                <property name='lifetime' value='Runtime'/>
                <property name='class_name' value='mpx.lib.xmlrpc.rna_xmlrpc.RNA_XMLRPC_Handler2'/>
                <property name='alias' value='rna_xmlrpc2'/>
              </config>
            </node>
          </node>
        </node>
        <node name='https_server' node_id='87f931f3-02d8-4d32-8c7d-2d1d7d8eab55' module='mpx.service.network.https.factory'  config_builder=''  inherant='true' description='Standard HTTPS server'>
          <config>
            <property name='__type__' value='service'/>
            <property name='common_name' value='auto'/>
            <property name='organizational_unit' value='Envenergy Self Signed Certificate'/>
            <property name='server_cert' value='${mpx.properties.CERTIFICATE_PEM_FILE}'/>
            <property name='port' value='${mpx.properties.HTTPS_PORT}'/>
            <property name='key_file' value='${mpx.properties.PRIVATE_KEY_FILE}'/>
            <property name='debug' value='0'/>
            <property name='country' value='US'/>
            <property name='enabled' value='1'/>
            <property name='state' value='CA'/>
            <property name='email' value='support@envenergy.com'/>
            <property name='thread_pool' value='3'/>
            <property name='city' value='Carpinteria'/>
            <property name='organization' value='Envenergy'/>
          </config>
          <node name='XMLRPCv2' node_id='07ff4603-ca5b-44ef-827b-361f8cffbba9' module='mpx.service.network.http.handlers.xmlrpc.factory'  config_builder=''  inherant='true' description=''>
          </node>
          <node name='config_file_handler' node_id='903a9305-debe-4fce-b385-d1395fd94696' module='mpx.service.network.http.handlers.config.factory'  config_builder=''  inherant='true' description='HTTP Configuration File Handler.'>
            <config>
              <property name='__type__' value='point'/>
              <property name='debug' value='0'/>
              <property name='safe_save' value='1'/>
              <property name='enabled' value='1'/>
              <property name='keep_backup' value='0'/>
            </config>
          </node>
          <node name='https_file_handler' node_id='476' module='mpx.service.network.http.request_handler.factory'  config_builder=''  inherant='true' description='HTTP file server'>
            <config>
              <property name='__type__' value='point'/>
              <property name='debug' value='0'/>
              <property name='put_enabled' value='1'/>
              <property name='delete_enabled' value='1'/>
              <property name='request_path' value='/'/>
              <property name='enabled' value='1'/>
              <property name='server_root' value='${mpx.properties.HTTPS_ROOT}'/>
            </config>
          </node>
          <node name='msglog_browser' node_id='450' module='mpx.lib.msglog.browser.factory'  config_builder=''  inherant='true' description='Enables browsing of the Mediator Framework Msglog'>
            <config>
              <property name='__type__' value='point'/>
              <property name='debug' value='0'/>
              <property name='request_path' value='^/msglog/.*|^/msglog$'/>
              <property name='enabled' value='1'/>
            </config>
          </node>
          <node name='node_browser' node_id='472' module='mpx.lib.node.browser.factory'  config_builder=''  inherant='true' description='Enables html browsing of Node Tree'>
            <config>
              <property name='__type__' value='point'/>
              <property name='debug' value='0'/>
              <property name='request_path' value='/nodebrowser'/>
              <property name='enabled' value='1'/>
            </config>
          </node>
          <node name='properties_browser' node_id='1246' module='mpx.service.network.http.properties_request_handler.PropertiesRequestHandler'  config_builder=''  inherant='true' description='Displays the current Properties of the system in an HTML page'>
            <config>
              <property name='__type__' value='point'/>
              <property name='debug' value='0'/>
              <property name='request_path' value='^/properties$'/>
              <property name='enabled' value='1'/>
            </config>
          </node>
        </node>
        <node name='rna' node_id='470' module='mpx.service.network.rna.factory'  config_builder=''  inherant='true' description='RPC service for nodes'>
          <config>
            <property name='__type__' value='point'/>
            <property name='debug' value='0'/>
            <property name='enabled' value='0'/>
            <property name='interface' value='all'/>
            <property name='port' value='5150'/>
          </config>
          <node name='configuration' node_id='478' module='mpx.service.configuration.factory'  config_builder=''  inherant='true' description='Runtime Configuration Tool'>
            <config>
              <property name='__type__' value='point'/>
              <property name='debug' value='0'/>
              <property name='enabled' value='1'/>
            </config>
          </node>
        </node>
        <node name='webdev' node_id='1251' module='mpx.service.network.webdev.WebDEV'  config_builder=''  inherant='true' description='Configuration options for web development'>
          <config>
            <property name='__type__' value='point'/>
            <property name='debug' value='0'/>
            <property name='allow_ftp' value='0'/>
            <property name='enable' value='0'/>
          </config>
        </node>
      </node>
      <node name='status' node_id='1088' module='mpx.service.status.factory'  config_builder=''  inherant='true' description='Mediator status indicator'>
        <config>
          <property name='__type__' value='point'/>
          <property name='debug' value='0'/>
        </config>
        <node name='resources' node_id='e83f54c0-772b-4263-b24f-23228c11cebc' module='mpx.service.status.resources.factory'  config_builder=''  inherant='true' description='Resources'>
          <node name='memory' node_id='e1f8cb2b-3ee4-4512-ac15-03aea67539ae' module='mpx.service.status.memory.factory'  config_builder=''  inherant='true' description='Memory Status'>
          </node>
          <node name='storage' node_id='6f5b6a27-191a-4336-9961-7d050dfbebf3' module='mpx.service.status.storage.factory'  config_builder=''  inherant='true' description='Storage Status'>
            <node name='root' node_id='7883838c-ddb3-42d3-b5c5-97f88478730f' module='mpx.service.status.storage.drive'  config_builder=''  inherant='true' description='Root Drive Storage Status'>
              <config>
                <property name='__type__' value='point'/>
                <property name='mount_point' value='/'/>
              </config>
              <node name='available' node_id='29945bea-9259-4281-b055-0786dd53f042' module='mpx.service.status.storage.drive_attribute'  config_builder=''  inherant='true' description='Amount Available (in bytes)'>
              </node>
              <node name='size' node_id='367ab751-330c-483b-8a95-83474d973198' module='mpx.service.status.storage.drive_attribute'  config_builder=''  inherant='true' description='Size of Drive (in bytes)'>
              </node>
              <node name='used' node_id='bf1f389f-b2b1-449c-b0a5-6719104618d2' module='mpx.service.status.storage.drive_attribute'  config_builder=''  inherant='true' description='Amount Used (in bytes)'>
              </node>
            </node>
          </node>
        </node>
      </node>
      <node name='time' node_id='612' module='mpx.service.time.Time'  config_builder='envenergy.ion.config.DateTimeSet'  inherant='true' description='Time service'>
        <node name='UTC' node_id='613' module='mpx.service.time.time_zone.UTC'  config_builder=''  inherant='true' description='Coordinated Universal Time'>
          <node name='day' node_id='617' module='mpx.service.time.time_attribute.TimeAttribute'  config_builder=''  inherant='true' description='The day as an int'>
          </node>
          <node name='hour' node_id='618' module='mpx.service.time.time_attribute.TimeAttribute'  config_builder=''  inherant='true' description='The hour as an int'>
          </node>
          <node name='milliseconds' node_id='621' module='mpx.service.time.time_attribute.MilliSeconds'  config_builder=''  inherant='true' description='The milliseconds as a float'>
          </node>
          <node name='minute' node_id='619' module='mpx.service.time.time_attribute.TimeAttribute'  config_builder=''  inherant='true' description='The minute as in int'>
          </node>
          <node name='month' node_id='616' module='mpx.service.time.time_attribute.TimeAttribute'  config_builder=''  inherant='true' description='The month as an int'>
          </node>
          <node name='second' node_id='620' module='mpx.service.time.time_attribute.TimeAttribute'  config_builder=''  inherant='true' description='The second as an int'>
          </node>
          <node name='weekday' node_id='623' module='mpx.service.time.time_attribute.TimeAttribute'  config_builder=''  inherant='true' description='The weekday as an int'>
          </node>
          <node name='year' node_id='615' module='mpx.service.time.time_attribute.TimeAttribute'  config_builder=''  inherant='true' description='The year'>
          </node>
        </node>
        <node name='local' node_id='614' module='mpx.service.time.time_zone.Local'  config_builder=''  inherant='true' description='Local time'>
          <node name='day' node_id='617' module='mpx.service.time.time_attribute.TimeAttribute'  config_builder=''  inherant='true' description='The day as an int'>
          </node>
          <node name='hour' node_id='618' module='mpx.service.time.time_attribute.TimeAttribute'  config_builder=''  inherant='true' description='The hour as an int'>
          </node>
          <node name='milliseconds' node_id='621' module='mpx.service.time.time_attribute.MilliSeconds'  config_builder=''  inherant='true' description='The milliseconds as a float'>
          </node>
          <node name='minute' node_id='619' module='mpx.service.time.time_attribute.TimeAttribute'  config_builder=''  inherant='true' description='The minute as in int'>
          </node>
          <node name='month' node_id='616' module='mpx.service.time.time_attribute.TimeAttribute'  config_builder=''  inherant='true' description='The month as an int'>
          </node>
          <node name='second' node_id='620' module='mpx.service.time.time_attribute.TimeAttribute'  config_builder=''  inherant='true' description='The second as an int'>
          </node>
          <node name='weekday' node_id='623' module='mpx.service.time.time_attribute.TimeAttribute'  config_builder=''  inherant='true' description='The weekday as an int'>
          </node>
          <node name='year' node_id='615' module='mpx.service.time.time_attribute.TimeAttribute'  config_builder=''  inherant='true' description='The year'>
          </node>
        </node>
        <node name='synch_continuous' node_id='800' module='mpx.service.time.time_synch.factory'  config_builder=''  inherant='true' description='Continuously synchronizes time with one or more time servers via a Broadband connection'>
          <config>
            <property name='__type__' value='service'/>
            <property name='debug' value='0'/>
            <property name='servers'>
              <list>
              </list>
            </property>
            <property name='connection_type' value='LAN'/>
            <property name='enable' value='0'/>
          </config>
        </node>
        <node name='synch_periodic' node_id='801' module='mpx.service.time.time_synch.factory'  config_builder=''  inherant='true' description='Periodically synchronizes time with one or more time servers over an intermittent Internet connection'>
          <config>
            <property name='__type__' value='service'/>
            <property name='debug' value='0'/>
            <property name='days' value='0'/>
            <property name='servers'>
              <list>
              </list>
            </property>
            <property name='connection_type' value='Dial out'/>
            <property name='hours' value='1'/>
            <property name='minutes' value='0'/>
            <property name='enable' value='0'/>
          </config>
        </node>
      </node>
    </node>
  </node>
</mpxconfig>

